ansible_generator/__init__.py
ansible_generator/directories.py
ansible_generator/files.py
ansible_generator/log.py
ansible_generator/main.py
ansible_generator/py.typed
ansible_generator/utilities.py
ansible_generator/version.py
ansible_generator-3.1.1.dist-info/entry_points.txt
ansible_generator-3.1.1.dist-info/LICENSE.txt
ansible_generator-3.1.1.dist-info/WHEEL
ansible_generator-3.1.1.dist-info/METADATA
ansible_generator-3.1.1.dist-info/RECORD
