Metadata-Version: 2.1
Name: ansible-generator
Version: 3.1.1
Summary: Ansible project generation tool
Home-page: https://github.com/kkirsche/ansible-generator
License: BSD-4-Clause
Keywords: development,ansible,generator
Author: Kevin Kirsche
Author-email: kev.kirsche@gmail.com
Requires-Python: >=3.8,<4.0
Classifier: Development Status :: 5 - Production/Stable
Classifier: Intended Audience :: Developers
Classifier: License :: Other/Proprietary License
Classifier: Programming Language :: Python :: 3
Classifier: Programming Language :: Python :: 3.10
Classifier: Programming Language :: Python :: 3.8
Classifier: Programming Language :: Python :: 3.9
Classifier: Topic :: Software Development :: Build Tools
Requires-Dist: ansible
Requires-Dist: sentry-sdk (>=1.9.0,<2.0.0)
Project-URL: Repository, https://github.com/kkirsche/ansible-generator
